tests/__init__.py
tests/conftest.py
tests/helpers.py
tests/test_corestate_accounts.py
tests/test_corestate_assets.py
tests/test_grpc_error_detail.py
tests/test_imports.py
tests/test_trading_submitorder.py
vegaapiclient/__init__.py
vegaapiclient/grpcclient.py
vegaapiclient/helpers.py
vegaapiclient/py.typed
vegaapiclient/vegacoreclient.py
vegaapiclient/vegacorestateclient.py
vegaapiclient/vegatradingdataclient.py
vegaapiclient/generated/__init__.py
vegaapiclient/generated/data_node/__init__.py
vegaapiclient/generated/data_node/api/__init__.py
vegaapiclient/generated/data_node/api/v1/__init__.py
vegaapiclient/generated/data_node/api/v1/trading_data_pb2.py
vegaapiclient/generated/data_node/api/v1/trading_data_pb2_grpc.py
vegaapiclient/generated/github/__init__.py
vegaapiclient/generated/github/com/__init__.py
vegaapiclient/generated/github/com/mwitkow/__init__.py
vegaapiclient/generated/github/com/mwitkow/go_proto_validators/__init__.py
vegaapiclient/generated/github/com/mwitkow/go_proto_validators/validator_pb2.py
vegaapiclient/generated/github/com/mwitkow/go_proto_validators/validator_pb2_grpc.py
vegaapiclient/generated/vega/__init__.py
vegaapiclient/generated/vega/assets_pb2.py
vegaapiclient/generated/vega/assets_pb2_grpc.py
vegaapiclient/generated/vega/chain_events_pb2.py
vegaapiclient/generated/vega/chain_events_pb2_grpc.py
vegaapiclient/generated/vega/governance_pb2.py
vegaapiclient/generated/vega/governance_pb2_grpc.py
vegaapiclient/generated/vega/markets_pb2.py
vegaapiclient/generated/vega/markets_pb2_grpc.py
vegaapiclient/generated/vega/vega_pb2.py
vegaapiclient/generated/vega/vega_pb2_grpc.py
vegaapiclient/generated/vega/api/__init__.py
vegaapiclient/generated/vega/api/v1/__init__.py
vegaapiclient/generated/vega/api/v1/core_pb2.py
vegaapiclient/generated/vega/api/v1/core_pb2_grpc.py
vegaapiclient/generated/vega/api/v1/corestate_pb2.py
vegaapiclient/generated/vega/api/v1/corestate_pb2_grpc.py
vegaapiclient/generated/vega/checkpoint/__init__.py
Vega_API_client-0.49.2.dist-info/LICENSE
Vega_API_client-0.49.2.dist-info/METADATA
Vega_API_client-0.49.2.dist-info/WHEEL
Vega_API_client-0.49.2.dist-info/top_level.txt
Vega_API_client-0.49.2.dist-info/RECORD
