Metadata-Version: 2.1
Name: Vega-API-client
Version: 0.49.2
Summary: Vega API client for gRPC
Home-page: https://github.com/vegaprotocol/api
Author: Vega
Author-email: hi@vega.xyz
License: UNKNOWN
Platform: UNKNOWN
Classifier: Programming Language :: Python :: 3
Classifier: License :: OSI Approved :: MIT License
Classifier: Operating System :: OS Independent
Requires-Python: >=3.7
Requires-Dist: googleapis-common-protos
Requires-Dist: grpcio
Requires-Dist: requests
